open_chat_api_client/__init__.py
open_chat_api_client/client.py
open_chat_api_client/errors.py
open_chat_api_client/py.typed
open_chat_api_client/types.py
open_chat_api_client/api/__init__.py
open_chat_api_client/api/bot/__init__.py
open_chat_api_client/api/bot/bot_login_create.py
open_chat_api_client/api/bot/bot_register_create.py
open_chat_api_client/api/chats/__init__.py
open_chat_api_client/api/chats/chats_by_title_create.py
open_chat_api_client/api/chats/chats_contacts_list.py
open_chat_api_client/api/chats/chats_delete_create.py
open_chat_api_client/api/chats/chats_list.py
open_chat_api_client/api/chats/chats_retrieve.py
open_chat_api_client/api/chats/chats_settings_create.py
open_chat_api_client/api/chats/chats_settings_retrieve.py
open_chat_api_client/api/chats/chats_with_list.py
open_chat_api_client/api/messages/__init__.py
open_chat_api_client/api/messages/messages_all_read_create.py
open_chat_api_client/api/messages/messages_list.py
open_chat_api_client/api/messages/messages_read_create.py
open_chat_api_client/api/messages/messages_send_create.py
open_chat_api_client/api/profile/__init__.py
open_chat_api_client/api/profile/profile_create_chat_create.py
open_chat_api_client/api/profile/profile_retrieve.py
open_chat_api_client/api/profile/profile_reveal_retrieve.py
open_chat_api_client/api/profile/profile_self_partial_update.py
open_chat_api_client/api/profile/profile_self_retrieve.py
open_chat_api_client/api/profile/profile_self_update.py
open_chat_api_client/api/public/__init__.py
open_chat_api_client/api/public/public_profiles_list.py
open_chat_api_client/api/user/__init__.py
open_chat_api_client/api/user/user_login_create.py
open_chat_api_client/api/user/user_logout_retrieve.py
open_chat_api_client/api/user/user_register_create.py
open_chat_api_client/api/user/user_self_retrieve.py
open_chat_api_client/models/__init__.py
open_chat_api_client/models/augmented_bot_user.py
open_chat_api_client/models/chat.py
open_chat_api_client-1.0.0.dist-info/LICENSE
open_chat_api_client-1.0.0.dist-info/METADATA
open_chat_api_client-1.0.0.dist-info/WHEEL
open_chat_api_client-1.0.0.dist-info/top_level.txt
open_chat_api_client-1.0.0.dist-info/RECORD
