Metadata-Version: 2.1
Name: open-chat-api-client
Version: 1.0.0
Summary: A client library for accessing Open Chat API
Requires-Python: >=3.8, <4
License-File: LICENSE
Requires-Dist: httpx <0.28.0,>=0.20.0
Requires-Dist: attrs >=21.3.0
Requires-Dist: python-dateutil <3,>=2.8.0
